shimpan/__init__.py
shimpan/__main__.py
shimpan/cli.py
shimpan/shim_alt.exe
shimpan/shim_scoop.exe
shimpan/version.txt
shimpan-1.4.0.dist-info/LICENSE
shimpan-1.4.0.dist-info/METADATA
shimpan-1.4.0.dist-info/WHEEL
shimpan-1.4.0.dist-info/entry_points.txt
shimpan-1.4.0.dist-info/top_level.txt
shimpan-1.4.0.dist-info/RECORD
