Metadata-Version: 2.2
Name: shimpan
Version: 1.4.0
Summary: shimpan
Classifier: Operating System :: OS Independent
Classifier: Programming Language :: Python
Classifier: Programming Language :: Python :: 3.10
Classifier: Programming Language :: Python :: 3.11
Requires-Python: >=3.10
License-File: LICENSE
Requires-Dist: tomli>=1.1.0; python_version < "3.11"
